cgi-bin/ta_labcode.v
// Lab 08

    module top(hz100,pb,ss7,ss6,ss5,ss4,ss3,ss2,ss1,ss0,left,right,red,green,blue);
        input hz100;
        input [20:0] pb;
        output [7:0] ss7;
        output [7:0] ss6;
        output [7:0] ss5;
        output [7:0] ss4;
        output [7:0] ss3;
        output [7:0] ss2;
        output [7:0] ss1;
        output [7:0] ss0;
        output [7:0] left;
        output [7:0] right;
        output red;
        output green;
        output blue;

        // Write your code below...






    reg [7:0] state;
    always @(posedge pb[16], posedge pb[17], posedge pb[18])
    begin

    if (pb[16] == 1'b1)
      state <= tog;
    else if (pb[17] == 1'b1) // 'X' button clears state
      state <= 8'b00000000;
    else
      state <= tog;

    end

    reg [7:0] tog = 8'b00000000;
    always @(posedge pb[0])
      tog[0] <= ~tog[0];
      always @(posedge pb[1])
      tog[1] <= ~tog[1];
      always @(posedge pb[2])
      tog[2] <= ~tog[2];
      always @(posedge pb[3])
      tog[3] <= ~tog[3];
      always @(posedge pb[4])
      tog[4] <= ~tog[4];
      always @(posedge pb[5])
      tog[5] <= ~tog[5];
      always @(posedge pb[6])
      tog[6] <= ~tog[6];
      always @(posedge pb[7])
      tog[7] <= ~tog[7];
      always @(posedge pb[8])
      tog[8] <= ~tog[8];

    assign left = tog;
    assign right = state;





    endmodule

cgi-bin/ta_testbench.sv
module lab08_tb();

logic [20:0] pb;
wire [7:0] left;
wire [7:0] right;

top t1 (.pb (pb), .left (left), .right (right));

task check_output;
  input string message;
  input value;
  input expected;
begin
  #5;
  if (value === expected || (value === 'x && expected == '0))
    $display ("CORRECT during check for %s, value = %b, expected = %b", message, value, expected);
  else
    $display ("INCORRECT during check for %s, value = %b, expected = %b", message, value, expected);
  #5;
end
endtask

initial begin
  // $dumpfile ("tbtest.vcd");
  // $dumpvars (0, lab08_tb);
  pb = 8'b00000000;
  check_output ("left initial setting", left, 8'b00000000);
  check_output ("right initial setting", right, 8'b00000000);

  pb [7:3] = 5'b11111;
  pb [7:3] = 5'b00000;
  check_output ("left after setting pb [7:3]", left, 8'b11111000);
  check_output ("right after setting pb [7:3]", right, 8'b00000000);

  pb [16] = 1'b1;
  pb [16] = 1'b0;
  check_output ("left after setting a clock edge", left, 8'b11111000);
  check_output ("right after setting a clock edge", right, 8'b11111000);

  pb [17] = 1'b1;
  pb [17] = 1'b0;
  check_output ("left after an asynchronous clear", left, 8'b11111000);
  check_output ("right after an asynchronous clear", right, 8'b00000000);

  pb [7:3] = 5'b11111;
  pb [7:3] = 5'b00000;
  check_output ("left after toggling pb a second time", left, 8'b00000000);
  check_output ("right after toggling pb a second time", right, 8'b00000000);

  pb [16] = 1'b1;
  pb [16] = 1'b0;
  check_output ("left after a second asynchronous clear", left, 8'b00000000);
  check_output ("right after a second asynchronous clear", right, 8'b00000000);
end

endmodule

cgi-bin/tbtest.vcd
$date
	Wed Jul 10 00:29:06 2019
$end
$version
	Icarus Verilog
$end
$timescale
	1s
$end
$scope module lab08_tb $end
$var wire 8 ! right [7:0] $end
$var wire 8 " left [7:0] $end
$var reg 21 # pb [20:0] $end
$scope module t1 $end
$var wire 1 $ blue $end
$var wire 1 % green $end
$var wire 1 & hz100 $end
$var wire 8 ' left [7:0] $end
$var wire 21 ( pb [20:0] $end
$var wire 1 ) red $end
$var wire 8 * right [7:0] $end
$var wire 8 + ss0 [7:0] $end
$var wire 8 , ss1 [7:0] $end
$var wire 8 - ss2 [7:0] $end
$var wire 8 . ss3 [7:0] $end
$var wire 8 / ss4 [7:0] $end
$var wire 8 0 ss5 [7:0] $end
$var wire 8 1 ss6 [7:0] $end
$var wire 8 2 ss7 [7:0] $end
$var reg 8 3 state [7:0] $end
$var reg 8 4 tog [7:0] $end
$upscope $end
$scope task check_output $end
$var reg 1 5 expected $end
$var reg 1 6 value $end
$upscope $end
$upscope $end
$enddefinitions $end
#0
$dumpvars
06
05
b0 4
bx 3
bz 2
bz 1
bz 0
bz /
bz .
bz -
bz ,
bz +
bx *
z)
b0 (
b0 '
z&
z%
z$
b0 #
b0 "
bx !
$end
#10
x6
#20
06
b0 #
b0 (
#30
x6
#40
06
b0 #
b0 (
#50
x6
#60
06
b0 #
b0 (
#70
x6
#80
06
b0 #
b0 (
#90
x6
#100
06
b0 #
b0 (
#110
x6
